pydal_limbo/__about__.py
pydal_limbo/__init__.py
pydal_limbo/adapter_limbo.py
pydal_limbo/limbo_dbapi2/dbapi2.py
pydal_limbo-0.1.1.dist-info/METADATA
pydal_limbo-0.1.1.dist-info/WHEEL
pydal_limbo-0.1.1.dist-info/RECORD
