Metadata-Version: 2.4
Name: pydal-limbo
Version: 0.1.1
Summary: Custom pyDAL adapter for limbo (SQLite rebuild)
Project-URL: Homepage, https://github.com/robinvandernoord/pydal-adapter-limbo
Author-email: Robin van der Noord <robin.vdn@educationwarehouse.nl>
Requires-Python: >=3.10
Requires-Dist: pydal
Requires-Dist: pylimbo
Provides-Extra: dev
Requires-Dist: hatch; extra == 'dev'
Requires-Dist: python-semantic-release<8; extra == 'dev'
